Workbook

Sheet Sheet1
A2: Tester note: Use plain user language. Avoid technical terms (token, endpoint, route, console) in test steps. | B2: Write tests using UI words testers can see: screen title, button, table, card, menu, message. | C2: Run in order: P0 first, then P1, then P2. | D2: Release gate: do all P0 tests first and resolve blockers before running P1/P2.
A3: AREA | B3: ID | C3: Page | D3: step# | E3: Test Step | F3: Expected Result | G3: Expected Status | H3: Actual Result | I3: Priority Level | J3: Solution | K3: Fix Applied | L3: Role Scope | M3: Traceability ID | N3: Bug Ticket | O3: Code Path Default | P3: Execution Tier
A4: Login Page - Authenticate users securely and establish/terminate application sessions.
B5: 1.01 | C5: Login | D5: 1 | E5: Navigate to the login URL | F5: Page loads with Username and Password fields | G5: Not Tested | I5: N/A | L5: User | M5: TRC-1.01-LOGIN | P5: P0 - Critical Path
B6: 1.02 | C6: Login | D6: 2 | E6: Enter valid credentials and click "Login" | F6: User is redirected to the Dashboard/Home page | G6: Not Tested | I6: N/A | L6: User | M6: TRC-1.02-LOGIN | P6: P0 - Critical Path
B7: 1.03 | C7: Login | D7: 3 | E7: Enter valid username but incorrect password | F7: Error message: "Invalid credentials" (or similar) | G7: Not Tested | I7: N/A | L7: User | M7: TRC-1.03-LOGIN | P7: P0 - Critical Path
B8: 1.04 | C8: Login | D8: 4 | E8: Leave both fields empty and click "Login" | F8: Browser or App displays "Required Field" validation | G8: Not Tested | I8: N/A | L8: User | M8: TRC-1.04-LOGIN | P8: P0 - Critical Path
B9: 1.05 | C9: Login | D9: 5 | E9: Enter an unregistered email/username | F9: Error message: "User does not exist" | G9: Not Tested | I9: N/A | L9: User | M9: TRC-1.05-LOGIN | P9: P0 - Critical Path
B10: 1.06 | C10: Session | D10: 1 | E10: Log in successfully, then click "Logout" | F10: User is redirected to login; back button doesn't re-log in | G10: Not Tested | I10: N/A | L10: User | M10: TRC-1.06-SESSION | P10: P0 - Critical Path
B11: 1.07 | C11: Session | D11: 2 | E11: Close browser tab without logging out and reopen | F11: User should remain logged in (if 'Remember Me' is active) | G11: Not Tested | I11: N/A | L11: User | M11: TRC-1.07-SESSION | P11: P0 - Critical Path
B12: 1.08 | C12: Security | D12: 3 | E12: Try to access Dashboard URL directly without logging in | F12: System redirects user back to the Login page | G12: Not Tested | I12: N/A | L12: User | M12: TRC-1.08-SECURITY | P12: P0 - Critical Path
A15: Home Page - League overview hub with standings, navigation, and assistant entry points.
B16: 2.01 | C16: Navigation | D16: 1 | E16: Click the hamburger menu icon | F16: Sidebar menu expands and is visible | G16: Not Tested | I16: N/A | L16: User | M16: TRC-2.01-NAVIGATION | P16: P2 - Extended Coverage
B17: 2.02 | C17: Navigation | D17: 2 | E17: Click the hamburger icon (or 'X') while expanded | F17: Sidebar menu collapses and is hidden | G17: Not Tested | I17: N/A | L17: User | M17: TRC-2.02-NAVIGATION | P17: P2 - Extended Coverage
B18: 2.03 | C18: UI/UX | D18: 1 | E18: Toggle the Dark/Light mode switch | F18: Theme colors update immediately across the UI | G18: Not Tested | I18: N/A | L18: User | M18: TRC-2.03-UI-UX | P18: P2 - Extended Coverage
B19: 2.04 | C19: UI/UX | D19: 2 | E19: Refresh page after changing theme | F19: Theme preference is persisted (Dark or Light) | G19: Not Tested | I19: N/A | L19: User | M19: TRC-2.04-UI-UX | P19: P2 - Extended Coverage
B20: 2.05 | C20: Teams | D20: 1 | E20: Click on any Team Name or Logo in the list | F20: User is redirected to that team's "Locker Room" page | G20: Not Tested | I20: N/A | L20: User | M20: TRC-2.05-TEAMS | P20: P2 - Extended Coverage
B21: 2.06 | C21: Teams | D21: 2 | E21: Click on the User's own team link | F21: User is redirected to their personal "Locker Room" | G21: Not Tested | I21: N/A | L21: User | M21: TRC-2.06-TEAMS | P21: P2 - Extended Coverage
B22: 2.07 | C22: Teams | D22: 1 | E22: Locate the League Standings table | F22: Table displays: Division, W/L/T, PF, and PA | G22: Not Tested | I22: N/A | L22: User | M22: TRC-2.07-TEAMS | P22: P2 - Extended Coverage
B23: 2.08 | C23: Teams | D23: 2 | E23: Verify data accuracy for "Team Nick Grant" | F23: Stats match the underlying database/API values | G23: Not Tested | I23: N/A | L23: User | M23: TRC-2.08-TEAMS | P23: P2 - Extended Coverage
B24: 2.09 | C24: Teams | D24: 1 | E24: Sort table by "PF" (Points For) | F24: Table reorders correctly from highest to lowest | G24: Not Tested | I24: N/A | L24: User | M24: TRC-2.09-TEAMS | P24: P2 - Extended Coverage
B25: 2.10 | C25: Content | D25: 1 | E25: Locate the "League News" section | F25: News feed displays latest league updates/posts | G25: Not Tested | I25: N/A | L25: User | M25: TRC-2.10-CONTENT | P25: P2 - Extended Coverage
B26: 2.11 | C26: AI/Chat | D26: 1 | E26: Click the Chat Assistant icon/button | F26: Chat interface expands/opens for user input | G26: Not Tested | I26: N/A | L26: User | M26: TRC-2.11-AI-CHAT | P26: P2 - Extended Coverage
B27: 2.12 | C27: AI/Chat | D27: 2 | E27: Click the collapse/close button on Chat | F27: Chat interface minimizes or hides from view | G27: Not Tested | I27: N/A | L27: User | M27: TRC-2.12-AI-CHAT | P27: P2 - Extended Coverage
... B32: 2.17 | C32: AI/Chat | D32: 5 | E32: Close chat and reopen | F32: Chat history persists (if implemented) | G32: Not Tested | I32: N/A | L32: User | M32: TRC-2.17-AI-CHAT | P32: P2 - Extended Coverage
A35: My Team Page - Team owner workspace for lineup decisions, roster changes, and trade actions.
B36: 3.01 | C36: My Team | D36: 1 | E36: Click Hamburger / Dark Mode / Chat | F36: UI components mirror Home Page behavior | G36: Not Tested | I36: N/A | L36: User | M36: TRC-3.01-MY-TEAM | P36: P2 - Extended Coverage
B37: 3.02 | C37: My Team | D37: 1 | E37: Ask Chat: "Who should I start this week?" | F37: AI analyzes roster/matchups and gives a suggestion | G37: Not Tested | I37: N/A | L37: User | M37: TRC-3.02-MY-TEAM | P37: P2 - Extended Coverage
B38: 3.03 | C38: Lineup | D38: 1 | E38: Toggle between "Recommend" and "Actual" views | F38: View shifts between AI-suggested and saved lineup | G38: Not Tested | I38: N/A | L38: User | M38: TRC-3.03-LINEUP | P38: P2 - Extended Coverage
B39: 3.04 | C39: Lineup | D39: 1 | E39: Select a different week from the dropdown | F39: Roster/Matchups update to reflect selected week | G39: Not Tested | I39: N/A | L39: User | M39: TRC-3.04-LINEUP | P39: P2 - Extended Coverage
B40: 3.05 | C40: Edit | D40: 1 | E40: Swap a Bench player with a Starter | F40: Position labels update; visual swap occurs | G40: Not Tested | I40: N/A | L40: User | M40: TRC-3.05-EDIT | P40: P2 - Extended Coverage
B41: 3.06 | C41: Edit | D41: 1 | E41: Move a player to a different week's lineup | F41: Change persists when navigating back to that week | G41: Not Tested | I41: N/A | L41: User | M41: TRC-3.06-EDIT | P41: P2 - Extended Coverage
B42: 3.07 | C42: Edit | D42: 1 | E42: Move Bench player to Taxi Squad (and vice versa) | F42: Player moves to/from the designated Taxi section | G42: Not Tested | I42: N/A | L42: User | M42: TRC-3.07-EDIT | P42: P2 - Extended Coverage
B43: 3.08 | C43: Edit | D43: 1 | E43: Exceed roster limit / invalid position start | F43: UI shows Red validation warning per Commish rules | G43: Not Tested | I43: N/A | L43: User | M43: TRC-3.08-EDIT | P43: P2 - Extended Coverage
B44: 3.09 | C44: Edit | D44: 1 | E44: Arrange a legal lineup | F44: UI shows Green validation; "Submit" is enabled | G44: Not Tested | I44: N/A | L44: User | M44: TRC-3.09-EDIT | P44: P0 - Critical Path
B45: 3.10 | C45: Edit | D45: 2 | E45: Click "Submit Roster" | F45: Success message appears; changes save to DB | G45: Not Tested | I45: N/A | L45: User | M45: TRC-3.10-EDIT | P45: P0 - Critical Path
B46: 3.11 | C46: Trade | D46: 1 | E46: Select an owner to trade with | F46: Both teams' rosters load side-by-side | G46: Not Tested | I46: N/A | L46: User | M46: TRC-3.11-TRADE | P46: P2 - Extended Coverage
B47: 3.12 | C47: Trade | D47: 1 | E47: Select players and add/request Draft Dollars | F47: Trade summary updates with selected assets | G47: Not Tested | I47: N/A | L47: User | M47: TRC-3.12-TRADE | P47: P2 - Extended Coverage
... B49: 3.14 | C49: Keepers | D49: 1 | E49: Select a player to keep | F49: [Known Issue] Verify if selection saves/fails | G49: Not Tested | I49: N/A | L49: User | M49: TRC-3.14-KEEPERS | P49: P2 - Extended Coverage
A52: Match-up Page - Weekly head-to-head views and Game Center details for matchup outcomes.
B53: 4.01 | C53: Match-up | D53: 1 | E53: Verify Header Data | F53: Shows: Nick Grant, Post Pacific League, [Division Name] | G53: Not Tested | I53: N/A | L53: User | M53: TRC-4.01-MATCH-UP | P53: P0 - Critical Path
B54: 4.02 | C54: Match-up | D54: 1 | E54: Toggle Week Number (Previous/Next) | F54: Match-ups update to show correct historical/future games | G54: Not Tested | I54: N/A | L54: User | M54: TRC-4.02-MATCH-UP | P54: P2 - Extended Coverage
B55: 4.03 | C55: Match-up | D55: 2 | E55: Enter Specific Week # in input field | F55: Page jumps directly to that week's data | G55: Not Tested | I55: N/A | L55: User | M55: TRC-4.03-MATCH-UP | P55: P2 - Extended Coverage
B56: 4.04 | C56: Match-up | D56: 1 | E56: Toggle "Actual" vs "Projected" | F56: Scores switch between live points and AI/Seed projections | G56: Not Tested | I56: N/A | L56: User | M56: TRC-4.04-MATCH-UP | P56: P2 - Extended Coverage
B57: 4.05 | C57: Match-up | D57: 1 | E57: Observe Live Scoring (during active game) | F57: Scores refresh/update without full page reload | G57: Not Tested | I57: N/A | L57: User | M57: TRC-4.05-MATCH-UP | P57: P2 - Extended Coverage
B58: 4.06 | C58: Match-up | D58: 1 | E58: Review Head-to-Head Content | F58: All league matchups are visible for the selected week | G58: Not Tested | I58: N/A | L58: User | M58: TRC-4.06-MATCH-UP | P58: P2 - Extended Coverage
B59: 4.07 | C59: Game Center | D59: 1 | E59: Click "Game Center" on a specific matchup | F59: Redirects to detailed breakdown of that specific game | G59: Not Tested | I59: N/A | L59: User | M59: TRC-4.07-GAME-CENTER | P59: P0 - Critical Path
B60: 4.08 | C60: Game Center | D60: 1 | E60: Review Team Details in Game Center | F60: Shows bench vs. starters, player status, and remaining PMR | G60: Not Tested | I60: N/A | L60: User | M60: TRC-4.08-GAME-CENTER | P60: P0 - Critical Path
B61: 4.09 | C61: Match-up | D61: 1 | E61: Locate "PMR" (Player Minutes Remaining) | F61: Displays total remaining game time for both teams | G61: Not Tested | I61: N/A | L61: User | M61: TRC-4.09-MATCH-UP | P61: P2 - Extended Coverage
B62: 4.10 | C62: Match-up | D62: 1 | E62: Simulate a Score Tie (if possible in DB) | F62: UI highlights the designated tie-breaker (e.g., Bench Pts) | G62: Not Tested | I62: N/A | L62: User | M62: TRC-4.10-MATCH-UP | P62: P2 - Extended Coverage
B63: 4.11 | C63: Match-up | D63: 1 | E63: Locate "Bench Points" for both teams | F63: Shows total points for players not in the starting lineup | G63: Not Tested | I63: N/A | L63: User | M63: TRC-4.11-MATCH-UP | P63: P2 - Extended Coverage
B64: 4.12 | C64: Match-up | D64: 2 | E64: Compare "Pain Index" (Bench vs. Starter) | F64: UI flags if a benched player outscored a starter | G64: Not Tested | I64: N/A | L64: User | M64: TRC-4.12-MATCH-UP | P64: P2 - Extended Coverage
... B68: 4.16 | C68: Chat | D68: 2 | E68: Ask: "Which matchup is the closest right now?" | F68: AI compares all live scores and identifies the smallest gap | G68: Not Tested | I68: N/A | L68: User | M68: TRC-4.16-CHAT | P68: P2 - Extended Coverage
A69: Cross-Cutting Quality - End-user resilience, permission boundaries, and data continuity checks.
B70: 5.01 | C70: Security | D70: 1 | E70: As a regular user, try to open the Commissioner area directly. | F70: You are blocked from Commissioner tools and shown the correct access message or redirect. | G70: Not Tested | I70: High | L70: User | M70: TRC-8.0-SECURITY-5.01 | P70: P0 - Critical Path
B71: 5.02 | C71: Security | D71: 2 | E71: As a regular user, try to open the Site Admin area directly. | F71: You are blocked from Site Admin tools and shown the correct access message or redirect. | G71: Not Tested | I71: High | L71: User | M71: TRC-0.0-SECURITY-5.02 | P71: P0 - Critical Path
B72: 5.03 | C72: Session | D72: 1 | E72: Stay signed in until your session ends, then try to save a lineup change. | F72: The app asks you to sign in again and clearly explains what to do next. | G72: Not Tested | I72: High | L72: User | M72: TRC-1.0-SESSION-5.03 | P72: P0 - Critical Path
B73: 5.04 | C73: Reliability | D73: 1 | E73: While opening Home or Matchups, briefly disconnect and reconnect your internet. | F73: You see a clear error/retry message and the app does not freeze. | G73: Not Tested | I73: High | L73: User | M73: TRC-6.0-RELIABILITY-5.04 | P73: P1 - Core Regression
B74: 5.05 | C74: Data Integrity | D74: 1 | E74: Make a legal lineup change, refresh the browser, then return to that same week and team. | F74: Your lineup change is still saved after refresh. | G74: Not Tested | I74: High | L74: User | M74: TRC-3.0-DATA-INTEGRITY-5.05 | P74: P1 - Core Regression
B75: 5.06 | C75: AI/Chat NFR | D75: 1 | E75: Ask the League Advisor one normal question from the chat box. | F75: You receive a clear answer within about 3 seconds. | G75: Not Tested | I75: Medium | L75: User | M75: TRC-6.0-AI-CHAT-NFR-5.06 | P75: P1 - Core Regression
B76: 5.07 | C76: AI/Chat NFR | D76: 2 | E76: Ask the League Advisor a long, multi-part question on a slower connection. | F76: If the response is delayed, the app shows a clear status/error message instead of freezing. | G76: Not Tested | I76: High | L76: User | M76: TRC-6.0-AI-CHAT-NFR-5.07 | P76: P1 - Core Regression
B77: 5.08 | C77: Usability | D77: 1 | E77: When a test fails, add a screenshot or link in the evidence field. | F77: The failure has enough detail for someone else to review and reproduce it. | G77: Not Tested | I77: Medium | L77: User | M77: TRC-TEST-OPS-USABILITY-5.08 | P77: P1 - Core Regression
A78: Full Frontend Page Coverage - Route/page-level UAT for all frontend pages in CERT.
B79: 6.01 | C79: Screen Location: Admin Settings > Manage Commissioners | D79: 1 | E79: From Admin Settings > Manage Commissioners, open the screen and confirm the page title, tables/sections, and primary buttons are visible. | F79: The screen opens correctly and the key items on the page are easy to find and use. | G79: Not Tested | I79: High | L79: Site Admin | M79: TRC-FE-PAGE-6.01 | O79: frontend/src/pages/admin/ManageCommissioners.jsx | P79: P1 - Core Regression
B80: 6.02 | C80: Screen Location: Admin Settings > Manage Commissioners | D80: 2 | E80: From Admin Settings > Manage Commissioners, complete one common user action (save, filter, navigate, or submit), then refresh the page. | F80: The action works as expected, and the same information is still correct after refresh. | G80: Not Tested | I80: Medium | L80: Site Admin | M80: TRC-FE-PAGE-6.02 | O80: frontend/src/pages/admin/ManageCommissioners.jsx | P80: P1 - Core Regression
B81: 6.03 | C81: Screen Location: Menu > Admin Settings | D81: 1 | E81: From Menu > Admin Settings, open the screen and confirm the page title, tables/sections, and primary buttons are visible. | F81: The screen opens correctly and the key items on the page are easy to find and use. | G81: Not Tested | I81: High | L81: Site Admin | M81: TRC-FE-PAGE-6.03 | O81: frontend/src/pages/admin/SiteAdmin.jsx | P81: P1 - Core Regression
B82: 6.04 | C82: Screen Location: Menu > Admin Settings | D82: 2 | E82: From Menu > Admin Settings, complete one common user action (save, filter, navigate, or submit), then refresh the page. | F82: The action works as expected, and the same information is still correct after refresh. | G82: Not Tested | I82: Medium | L82: Site Admin | M82: TRC-FE-PAGE-6.04 | O82: frontend/src/pages/admin/SiteAdmin.jsx | P82: P1 - Core Regression
B83: 6.05 | C83: Screen Location: Menu > Analytics | D83: 1 | E83: From Menu > Analytics, open the screen and confirm the page title, tables/sections, and primary buttons are visible. | F83: The screen opens correctly and the key items on the page are easy to find and use. | G83: Not Tested | I83: High | L83: User | M83: TRC-FE-PAGE-6.05 | O83: frontend/src/pages/Analytics/AnalyticsDashboard.jsx | P83: P1 - Core Regression
B84: 6.06 | C84: Screen Location: Menu > Analytics | D84: 2 | E84: From Menu > Analytics, complete one common user action (save, filter, navigate, or submit), then refresh the page. | F84: The action works as expected, and the same information is still correct after refresh. | G84: Not Tested | I84: Medium | L84: User | M84: TRC-FE-PAGE-6.06 | O84: frontend/src/pages/Analytics/AnalyticsDashboard.jsx | P84: P1 - Core Regression
B85: 6.07 | C85: Screen Location: Menu > Report a Bug | D85: 1 | E85: From Menu > Report a Bug, open the screen and confirm the page title, tables/sections, and primary buttons are visible. | F85: The screen opens correctly and the key items on the page are easy to find and use. | G85: Not Tested | I85: High | L85: User | M85: TRC-FE-PAGE-6.07 | O85: frontend/src/pages/BugReport.jsx | P85: P1 - Core Regression
B86: 6.08 | C86: Screen Location: Menu > Report a Bug | D86: 2 | E86: From Menu > Report a Bug, complete one common user action (save, filter, navigate, or submit), then refresh the page. | F86: The action works as expected, and the same information is still correct after refresh. | G86: Not Tested | I86: Medium | L86: User | M86: TRC-FE-PAGE-6.08 | O86: frontend/src/pages/BugReport.jsx | P86: P1 - Core Regression
B87: 6.09 | C87: Screen Location: Commissioner screens | D87: 1 | E87: From Commissioner screens, open the screen and confirm the page title, tables/sections, and primary buttons are visible. | F87: The screen opens correctly and the key items on the page are easy to find and use. | G87: Not Tested | I87: High | L87: Commissioner | M87: TRC-FE-PAGE-6.09 | O87: frontend/src/pages/commissioner/CommishAdmin.jsx | P87: P1 - Core Regression
B88: 6.10 | C88: Screen Location: Commissioner screens | D88: 2 | E88: From this Commissioner screen, change a setting and click Save, then refresh the page. | F88: The saved setting remains correct after refresh and is visible to users where applicable. | G88: Not Tested | I88: Medium | L88: Commissioner | M88: TRC-FE-PAGE-6.10 | O88: frontend/src/pages/commissioner/CommishAdmin.jsx | P88: P0 - Critical Path
B89: 6.11 | C89: Screen Location: Menu > Commissioner | D89: 1 | E89: From Menu > Commissioner, open the screen and confirm the page title, tables/sections, and primary buttons are visible. | F89: The screen opens correctly and the key items on the page are easy to find and use. | G89: Not Tested | I89: High | L89: Commissioner | M89: TRC-FE-PAGE-6.11 | O89: frontend/src/pages/commissioner/CommissionerDashboard.jsx | P89: P1 - Core Regression
B90: 6.12 | C90: Screen Location: Menu > Commissioner | D90: 2 | E90: From this Commissioner screen, change a setting and click Save, then refresh the page. | F90: The saved setting remains correct after refresh and is visible to users where applicable. | G90: Not Tested | I90: Medium | L90: Commissioner | M90: TRC-FE-PAGE-6.12 | O90: frontend/src/pages/commissioner/CommissionerDashboard.jsx | P90: P0 - Critical Path
... B146: 6.68 | C146: Screen Location: Menu > Waiver Wire | D146: 2 | E146: From Menu > Waiver Wire, submit a waiver claim and then refresh the page. | F146: The waiver claim is accepted and still appears correctly after refresh. | G146: Not Tested | I146: Medium | L146: User | M146: TRC-FE-PAGE-6.68 | O146: frontend/src/pages/WaiverWire.jsx | P146: P0 - Critical Path
A147: Full Frontend Component Coverage - Reusable and page-local component behavior checks.
B148: 7.01 | C148: UI Element: Admin Action Card | D148: 1 | E148: On Admin Settings screens, find the Admin Action Card and test it in at least two states (for example default and after a click or selection). | F148: The element is clear, reacts correctly, and does not break nearby tables, cards, or page layout. | G148: Not Tested | I148: Medium | L148: Site Admin | M148: TRC-FE-COMP-7.01 | O148: frontend/src/components/admin/AdminActionCard.jsx | P148: P1 - Core Regression
B149: 7.02 | C149: UI Element: Admin Settings Element | D149: 1 | E149: On Admin Settings screens, find the Admin Settings Element and test it in at least two states (for example default and after a click or selection). | F149: The element is clear, reacts correctly, and does not break nearby tables, cards, or page layout. | G149: Not Tested | I149: Medium | L149: Site Admin | M149: TRC-FE-COMP-7.02 | O149: frontend/src/components/admin/AdminSettings.jsx | P149: P1 - Core Regression
B150: 7.03 | C150: UI Element: Admin Nav Element | D150: 1 | E150: On the related app screen, find the Admin Nav Element and test it in at least two states (for example default and after a click or selection). | F150: The element is clear, reacts correctly, and does not break nearby tables, cards, or page layout. | G150: Not Tested | I150: Medium | L150: User | M150: TRC-FE-COMP-7.03 | O150: frontend/src/components/AdminNav.jsx | P150: P1 - Core Regression
B151: 7.04 | C151: UI Element: Draft Value Board Element | D151: 1 | E151: On Analytics and chart sections, find the Draft Value Board Element and test it in at least two states (for example default and after a click or selection). | F151: The element is clear, reacts correctly, and does not break nearby tables, cards, or page layout. | G151: Not Tested | I151: Medium | L151: User | M151: TRC-FE-COMP-7.04 | O151: frontend/src/components/charts/DraftValueBoard.jsx | P151: P1 - Core Regression
B152: 7.05 | C152: UI Element: Manager Efficiency Leaderboard Element | D152: 1 | E152: On Analytics and chart sections, find the Manager Efficiency Leaderboard Element and test it in at least two states (for example default and after a click or selection). | F152: The element is clear, reacts correctly, and does not break nearby tables, cards, or page layout. | G152: Not Tested | I152: Medium | L152: User | M152: TRC-FE-COMP-7.05 | O152: frontend/src/components/charts/ManagerEfficiencyLeaderboard.jsx | P152: P1 - Core Regression
B153: 7.06 | C153: UI Element: Manager Trend Chart Element | D153: 1 | E153: On Analytics and chart sections, find the Manager Trend Chart Element and test it in at least two states (for example default and after a click or selection). | F153: The element is clear, reacts correctly, and does not break nearby tables, cards, or page layout. | G153: Not Tested | I153: Medium | L153: User | M153: TRC-FE-COMP-7.06 | O153: frontend/src/components/charts/ManagerTrendChart.jsx | P153: P1 - Core Regression
B154: 7.07 | C154: UI Element: Player Heatmap Element | D154: 1 | E154: On Analytics and chart sections, find the Player Heatmap Element and test it in at least two states (for example default and after a click or selection). | F154: The element is clear, reacts correctly, and does not break nearby tables, cards, or page layout. | G154: Not Tested | I154: Medium | L154: User | M154: TRC-FE-COMP-7.07 | O154: frontend/src/components/charts/PlayerHeatmap.jsx | P154: P1 - Core Regression
B155: 7.08 | C155: UI Element: Rivalry Graph Element | D155: 1 | E155: On Analytics and chart sections, find the Rivalry Graph Element and test it in at least two states (for example default and after a click or selection). | F155: The element is clear, reacts correctly, and does not break nearby tables, cards, or page layout. | G155: Not Tested | I155: Medium | L155: User | M155: TRC-FE-COMP-7.08 | O155: frontend/src/components/charts/RivalryGraph.jsx | P155: P1 - Core Regression
B156: 7.09 | C156: UI Element: Trade Analyzer Element | D156: 1 | E156: On Analytics and chart sections, find the Trade Analyzer Element and test it in at least two states (for example default and after a click or selection). | F156: The element is clear, reacts correctly, and does not break nearby tables, cards, or page layout. | G156: Not Tested | I156: Medium | L156: User | M156: TRC-FE-COMP-7.09 | O156: frontend/src/components/charts/TradeAnalyzer.jsx | P156: P1 - Core Regression
B157: 7.10 | C157: UI Element: Weekly Matchup Chart Element | D157: 1 | E157: On Analytics and chart sections, find the Weekly Matchup Chart Element and test it in at least two states (for example default and after a click or selection). | F157: The element is clear, reacts correctly, and does not break nearby tables, cards, or page layout. | G157: Not Tested | I157: Medium | L157: User | M157: TRC-FE-COMP-7.10 | O157: frontend/src/components/charts/WeeklyMatchupChart.jsx | P157: P1 - Core Regression
B158: 7.11 | C158: UI Element: Chat Interface Element | D158: 1 | E158: On League Advisor chat area, find the Chat Interface Element and test it in at least two states (for example default and after a click or selection). | F158: The element is clear, reacts correctly, and does not break nearby tables, cards, or page layout. | G158: Not Tested | I158: Medium | L158: User | M158: TRC-FE-COMP-7.11 | O158: frontend/src/components/chat/ChatInterface.jsx | P158: P1 - Core Regression
B159: 7.12 | C159: UI Element: Gemini Badge Element | D159: 1 | E159: On League Advisor chat area, find the Gemini Badge Element and test it in at least two states (for example default and after a click or selection). | F159: The element is clear, reacts correctly, and does not break nearby tables, cards, or page layout. | G159: Not Tested | I159: Medium | L159: User | M159: TRC-FE-COMP-7.12 | O159: frontend/src/components/chat/GeminiBadge.jsx | P159: P1 - Core Regression
... B190: 7.43 | C190: UI Element: Playoff Bracket Section | D190: 1 | E190: On Home screen sections, find the Playoff Bracket Section and test it in at least two states (for example default and after a click or selection). | F190: The element is clear, reacts correctly, and does not break nearby tables, cards, or page layout. | G190: Not Tested | I190: Medium | L190: User | M190: TRC-FE-COMP-7.43 | O190: frontend/src/pages/home/components/BracketAccordion.jsx | P190: P1 - Core Regression
A191: Commissioner waiver history - stability and recovery regression
B192: 6.69 | C192: Commissioner > Manage Waiver Rules | D192: 1 | E192: Open Commissioner > Manage Waiver Rules in a league with completed claims, then refresh the page. | F192: The claim history shows the selected league's completed claims and remains correct after refresh. | G192: Not Tested | I192: High | L192: Commissioner | M192: TRC-STABILITY-6.69 | N192: https://github.com/NPGrant81/fantasy-football-pi/issues/534 | O192: frontend/src/pages/commissioner/ManageWaiverRules.jsx | P192: P0 - Critical Path
B193: 6.70 | C193: Commissioner > Manage Waiver Rules | D193: 1 | E193: Open Commissioner > Manage Waiver Rules in a league with no claims. | F193: The history shows no claims, without an error or claims from another league. | G193: Not Tested | I193: High | L193: Commissioner | M193: TRC-STABILITY-6.70 | N193: https://github.com/NPGrant81/fantasy-football-pi/issues/534 | O193: frontend/src/pages/commissioner/ManageWaiverRules.jsx | P193: P1 - Core Regression
B194: 6.71 | C194: Commissioner > Manage Waiver Rules | D194: 1 | E194: With QA simulating a temporary history-loading failure, open Manage Waiver Rules. Restore access and select Retry waiver history. | F194: A clear error appears instead of empty success. Retry loads the claim history after access is restored. | G194: Not Tested | I194: High | L194: Commissioner | M194: TRC-STABILITY-6.71 | N194: https://github.com/NPGrant81/fantasy-football-pi/issues/534 | O194: frontend/src/pages/commissioner/ManageWaiverRules.jsx | P194: P1 - Core Regression
B195: 6.72 | C195: Commissioner > Manage Waiver Rules | D195: 1 | E195: With QA restricting history access, open Manage Waiver Rules and try Retry waiver history. | F195: A clear permission message remains visible and no restricted claims are displayed. | G195: Not Tested | I195: High | L195: Commissioner | M195: TRC-STABILITY-6.72 | N195: https://github.com/NPGrant81/fantasy-football-pi/issues/534 | O195: frontend/src/pages/commissioner/ManageWaiverRules.jsx | P195: P0 - Critical Path
B196: 6.73 | C196: Commissioner > Manage Waiver Rules | D196: 1 | E196: Delay loading the first league's history with QA, switch to another league, then allow both loads to finish. | F196: Only the newly selected league's history appears; the delayed first league does not replace it. | G196: Not Tested | I196: High | L196: Commissioner | M196: TRC-STABILITY-6.73 | N196: https://github.com/NPGrant81/fantasy-football-pi/issues/534 | O196: frontend/src/pages/commissioner/ManageWaiverRules.jsx | P196: P0 - Critical Path
B197: 6.74 | C197: Commissioner > Manage Waiver Rules | D197: 1 | E197: Open Commissioner > Manage Waiver Rules directly in a new tab, then refresh the page. | F197: The app page loads normally and claim history is either shown or reports a clear, retryable error. | G197: Not Tested | I197: High | L197: Commissioner | M197: TRC-STABILITY-6.74 | N197: https://github.com/NPGrant81/fantasy-football-pi/issues/532 | O197: frontend/src/pages/commissioner/ManageWaiverRules.jsx | P197: P1 - Core Regression

Sheet Dropdown_Lists
A1: Not Tested | B1: High | C1: Yes | D1: User | E1: New | F1: Critical | G1: ExecutionTier
A2: In Progress | B2: Medium | C2: No | D2: Commissioner | E2: Triaged | F2: High | G2: P0 - Critical Path
A3: Pass | B3: Low | C3: Partial | D3: Site Admin | E3: In Progress | F3: Medium | G3: P1 - Core Regression
A4: Fail | B4: N/A | C4: N/A | D4: Mixed | E4: Fixed | F4: Low | G4: P2 - Extended Coverage
A5: Blocked | E5: Retest
E6: Closed
E7: Deferred

Sheet Defect_Rollup
A1: Master Defect ID | B1: Source Test ID | C1: Traceability ID | D1: Summary | E1: Rollup Status | F1: Severity | G1: Priority | H1: Environment | I1: Role Scope | J1: Bug Ticket | K1: Area/Page | L1: Candidate Code Path | M1: Repro Steps | N1: Expected Result | O1: Actual Result | P1: Evidence Link | Q1: Owner | R1: Notes | S1: Date Reported | T1: Last Updated | V1: Roll-up Metrics
H2: CERT | L2: =IFERROR(_xludf.XLOOKUP(C2,CodePath_Defaults!A:A,CodePath_Defaults!D:D,""),IFERROR(_xludf.XLOOKUP(B2,CodePath_Defaults!B:B,CodePath_Defaults!D:D,""),"")) | T2: 2026-03-07 | V2: Total Defects | W2: =COUNTIF(A2:A2000,"<>") -> 0
L3: =IFERROR(_xludf.XLOOKUP(C3,CodePath_Defaults!A:A,CodePath_Defaults!D:D,""),IFERROR(_xludf.XLOOKUP(B3,CodePath_Defaults!B:B,CodePath_Defaults!D:D,""),"")) | T3: 2026-03-07 | V3: Open Defects | W3: =SUM(COUNTIF(E2:E2000,{"New","Triaged","In Progress","Retest"})) -> 0
L4: =IFERROR(_xludf.XLOOKUP(C4,CodePath_Defaults!A:A,CodePath_Defaults!D:D,""),IFERROR(_xludf.XLOOKUP(B4,CodePath_Defaults!B:B,CodePath_Defaults!D:D,""),"")) | T4: 2026-03-07 | V4: Closed Defects | W4: =COUNTIF(E2:E2000,"Closed") -> 0
L5: =IFERROR(_xludf.XLOOKUP(C5,CodePath_Defaults!A:A,CodePath_Defaults!D:D,""),IFERROR(_xludf.XLOOKUP(B5,CodePath_Defaults!B:B,CodePath_Defaults!D:D,""),"")) | T5: 2026-03-07 | V5: Deferred Defects | W5: =COUNTIF(E2:E2000,"Deferred") -> 0
L6: =IFERROR(_xludf.XLOOKUP(C6,CodePath_Defaults!A:A,CodePath_Defaults!D:D,""),IFERROR(_xludf.XLOOKUP(B6,CodePath_Defaults!B:B,CodePath_Defaults!D:D,""),"")) | T6: 2026-03-07 | V6: Critical Severity | W6: =COUNTIF(F2:F2000,"Critical") -> 0
L7: =IFERROR(_xludf.XLOOKUP(C7,CodePath_Defaults!A:A,CodePath_Defaults!D:D,""),IFERROR(_xludf.XLOOKUP(B7,CodePath_Defaults!B:B,CodePath_Defaults!D:D,""),"")) | T7: 2026-03-07 | V7: High Severity | W7: =COUNTIF(F2:F2000,"High") -> 0
L8: =IFERROR(_xludf.XLOOKUP(C8,CodePath_Defaults!A:A,CodePath_Defaults!D:D,""),IFERROR(_xludf.XLOOKUP(B8,CodePath_Defaults!B:B,CodePath_Defaults!D:D,""),"")) | T8: 2026-03-07 | V8: Medium Severity | W8: =COUNTIF(F2:F2000,"Medium") -> 0
L9: =IFERROR(_xludf.XLOOKUP(C9,CodePath_Defaults!A:A,CodePath_Defaults!D:D,""),IFERROR(_xludf.XLOOKUP(B9,CodePath_Defaults!B:B,CodePath_Defaults!D:D,""),"")) | T9: 2026-03-07 | V9: Low Severity | W9: =COUNTIF(F2:F2000,"Low") -> 0
L10: =IFERROR(_xludf.XLOOKUP(C10,CodePath_Defaults!A:A,CodePath_Defaults!D:D,""),IFERROR(_xludf.XLOOKUP(B10,CodePath_Defaults!B:B,CodePath_Defaults!D:D,""),"")) | T10: 2026-03-07 | V10: CERT Tagged | W10: =COUNTIF(H2:H2000,"CERT") -> 1
L11: =IFERROR(_xludf.XLOOKUP(C11,CodePath_Defaults!A:A,CodePath_Defaults!D:D,""),IFERROR(_xludf.XLOOKUP(B11,CodePath_Defaults!B:B,CodePath_Defaults!D:D,""),"")) | T11: 2026-03-07
L12: =IFERROR(_xludf.XLOOKUP(C12,CodePath_Defaults!A:A,CodePath_Defaults!D:D,""),IFERROR(_xludf.XLOOKUP(B12,CodePath_Defaults!B:B,CodePath_Defaults!D:D,""),"")) | T12: 2026-03-07
L13: =IFERROR(_xludf.XLOOKUP(C13,CodePath_Defaults!A:A,CodePath_Defaults!D:D,""),IFERROR(_xludf.XLOOKUP(B13,CodePath_Defaults!B:B,CodePath_Defaults!D:D,""),"")) | T13: 2026-03-07
L14: =IFERROR(_xludf.XLOOKUP(C14,CodePath_Defaults!A:A,CodePath_Defaults!D:D,""),IFERROR(_xludf.XLOOKUP(B14,CodePath_Defaults!B:B,CodePath_Defaults!D:D,""),"")) | T14: 2026-03-07
L15: =IFERROR(_xludf.XLOOKUP(C15,CodePath_Defaults!A:A,CodePath_Defaults!D:D,""),IFERROR(_xludf.XLOOKUP(B15,CodePath_Defaults!B:B,CodePath_Defaults!D:D,""),"")) | T15: 2026-03-07
L16: =IFERROR(_xludf.XLOOKUP(C16,CodePath_Defaults!A:A,CodePath_Defaults!D:D,""),IFERROR(_xludf.XLOOKUP(B16,CodePath_Defaults!B:B,CodePath_Defaults!D:D,""),"")) | T16: 2026-03-07
L17: =IFERROR(_xludf.XLOOKUP(C17,CodePath_Defaults!A:A,CodePath_Defaults!D:D,""),IFERROR(_xludf.XLOOKUP(B17,CodePath_Defaults!B:B,CodePath_Defaults!D:D,""),"")) | T17: 2026-03-07
L18: =IFERROR(_xludf.XLOOKUP(C18,CodePath_Defaults!A:A,CodePath_Defaults!D:D,""),IFERROR(_xludf.XLOOKUP(B18,CodePath_Defaults!B:B,CodePath_Defaults!D:D,""),"")) | T18: 2026-03-07
L19: =IFERROR(_xludf.XLOOKUP(C19,CodePath_Defaults!A:A,CodePath_Defaults!D:D,""),IFERROR(_xludf.XLOOKUP(B19,CodePath_Defaults!B:B,CodePath_Defaults!D:D,""),"")) | T19: 2026-03-07
L20: =IFERROR(_xludf.XLOOKUP(C20,CodePath_Defaults!A:A,CodePath_Defaults!D:D,""),IFERROR(_xludf.XLOOKUP(B20,CodePath_Defaults!B:B,CodePath_Defaults!D:D,""),"")) | T20: 2026-03-07
L21: =IFERROR(_xludf.XLOOKUP(C21,CodePath_Defaults!A:A,CodePath_Defaults!D:D,""),IFERROR(_xludf.XLOOKUP(B21,CodePath_Defaults!B:B,CodePath_Defaults!D:D,""),"")) | T21: 2026-03-07
L22: =IFERROR(_xludf.XLOOKUP(C22,CodePath_Defaults!A:A,CodePath_Defaults!D:D,""),IFERROR(_xludf.XLOOKUP(B22,CodePath_Defaults!B:B,CodePath_Defaults!D:D,""),"")) | T22: 2026-03-07
... L2000: =IFERROR(_xludf.XLOOKUP(C2000,CodePath_Defaults!A:A,CodePath_Defaults!D:D,""),IFERROR(_xludf.XLOOKUP(B2000,CodePath_Defaults!B:B,CodePath_Defaults!D:D,""),"")) | T2000: 2026-03-07

Sheet CodePath_Defaults
A1: Traceability ID | B1: Source Test ID | C1: Area/Page | D1: Code Path Default | E1: Role Scope
A2: TRC-1.01-LOGIN | B2: 1.01 | C2: Login | E2: User
A3: TRC-1.02-LOGIN | B3: 1.02 | C3: Login | E3: User
A4: TRC-1.03-LOGIN | B4: 1.03 | C4: Login | E4: User
A5: TRC-1.04-LOGIN | B5: 1.04 | C5: Login | E5: User
A6: TRC-1.05-LOGIN | B6: 1.05 | C6: Login | E6: User
A7: TRC-1.06-SESSION | B7: 1.06 | C7: Session | E7: User
A8: TRC-1.07-SESSION | B8: 1.07 | C8: Session | E8: User
A9: TRC-1.08-SECURITY | B9: 1.08 | C9: Security | E9: User
A10: TRC-2.01-NAVIGATION | B10: 2.01 | C10: Navigation | E10: User
A11: TRC-2.02-NAVIGATION | B11: 2.02 | C11: Navigation | E11: User
A12: TRC-2.03-UI-UX | B12: 2.03 | C12: UI/UX | E12: User
A13: TRC-2.04-UI-UX | B13: 2.04 | C13: UI/UX | E13: User
... A64: TRC-TEST-OPS-USABILITY-5.08 | B64: 5.08 | C64: Usability | E64: User
A65: TRC-FE-PAGE-6.01 | B65: 6.01 | C65: Page:ManageCommissioners | D65: frontend/src/pages/admin/ManageCommissioners.jsx | E65: Site Admin
A66: TRC-FE-PAGE-6.02 | B66: 6.02 | C66: Page:ManageCommissioners | D66: frontend/src/pages/admin/ManageCommissioners.jsx | E66: Site Admin
A67: TRC-FE-PAGE-6.03 | B67: 6.03 | C67: Page:SiteAdmin | D67: frontend/src/pages/admin/SiteAdmin.jsx | E67: Site Admin
A68: TRC-FE-PAGE-6.04 | B68: 6.04 | C68: Page:SiteAdmin | D68: frontend/src/pages/admin/SiteAdmin.jsx | E68: Site Admin
A69: TRC-FE-PAGE-6.05 | B69: 6.05 | C69: Page:AnalyticsDashboard | D69: frontend/src/pages/Analytics/AnalyticsDashboard.jsx | E69: User
A70: TRC-FE-PAGE-6.06 | B70: 6.06 | C70: Page:AnalyticsDashboard | D70: frontend/src/pages/Analytics/AnalyticsDashboard.jsx | E70: User
A71: TRC-FE-PAGE-6.07 | B71: 6.07 | C71: Page:BugReport | D71: frontend/src/pages/BugReport.jsx | E71: User
A72: TRC-FE-PAGE-6.08 | B72: 6.08 | C72: Page:BugReport | D72: frontend/src/pages/BugReport.jsx | E72: User
A73: TRC-FE-PAGE-6.09 | B73: 6.09 | C73: Page:CommishAdmin | D73: frontend/src/pages/commissioner/CommishAdmin.jsx | E73: Commissioner
A74: TRC-FE-PAGE-6.10 | B74: 6.10 | C74: Page:CommishAdmin | D74: frontend/src/pages/commissioner/CommishAdmin.jsx | E74: Commissioner
A75: TRC-FE-PAGE-6.11 | B75: 6.11 | C75: Page:CommissionerDashboard | D75: frontend/src/pages/commissioner/CommissionerDashboard.jsx | E75: Commissioner
A76: TRC-FE-PAGE-6.12 | B76: 6.12 | C76: Page:CommissionerDashboard | D76: frontend/src/pages/commissioner/CommissionerDashboard.jsx | E76: Commissioner
... A175: TRC-FE-COMP-7.43 | B175: 7.43 | C175: Component:BracketAccordion | D175: frontend/src/pages/home/components/BracketAccordion.jsx | E175: User
